pypowergames/pingpong.py
pypowergames/tictactoe.py
pypowergames-1.0.1.dist-info/LICENSE.txt
pypowergames-1.0.1.dist-info/METADATA
pypowergames-1.0.1.dist-info/WHEEL
pypowergames-1.0.1.dist-info/entry_points.txt
pypowergames-1.0.1.dist-info/top_level.txt
pypowergames-1.0.1.dist-info/RECORD
